zinnia_tinymce/__init__.py
zinnia_tinymce/admin.py
zinnia_tinymce/models.py
zinnia_tinymce/tests.py
zinnia_tinymce/views.py
zinnia_tinymce/migrations/0001_initial.py
zinnia_tinymce/migrations/__init__.py
zinnia_tinymce/static/zinnia_tinymce/css/filebrowser.css
zinnia_tinymce/templates/admin/zinnia/entry/tinymce_textareas.js
zinnia_tinymce/templates/zinnia_tinymce/entry_links.js
zinnia_tinymce/templates/zinnia_tinymce/file_links.js
zinnia_tinymce/templates/zinnia_tinymce/filebrowser.js
zinnia_tinymce/templates/zinnia_tinymce/filemodel_form.html
zinnia_tinymce/templates/zinnia_tinymce/image_links.js
zinnia_tinymce/urls/__init__.py
zinnia_tinymce/urls/filebrowser.py
zinnia_tinymce/urls/links.py
zinnia_wysiwyg_tinymce-1.4.dist-info/DESCRIPTION.rst
zinnia_wysiwyg_tinymce-1.4.dist-info/METADATA
zinnia_wysiwyg_tinymce-1.4.dist-info/RECORD
zinnia_wysiwyg_tinymce-1.4.dist-info/WHEEL
zinnia_wysiwyg_tinymce-1.4.dist-info/metadata.json
zinnia_wysiwyg_tinymce-1.4.dist-info/top_level.txt
